Metadata-Version: 2.1
Name: bibbib
Version: 0.0.1
Summary: bibbib - A Simple BiBTeX linter.
Home-page: https://github.com/adriancaruana/bibbib
Author: Adrian Caruana
Author-email: adrian@adriancaruana.com
License: MIT
Keywords: BiBTeX,linter,validator
Platform: UNKNOWN
Classifier: License :: OSI Approved :: MIT License
Classifier: Programming Language :: Python :: 3.9
